{
    "type":"minecraft:generic",
    "pools":[
        {
            "functions":[
                {
                    "function":"minecraft:set_name",
                    "name":{
                        "translate":"item.hats.glasses.half_rim.name"
                    }
                },
                {
                    "function":"set_nbt",
                    "tag":"{CustomModelData:3142, Tags:[\"hats.hat\", \"hats.hat.type.half_rim_glasses\"]}"
                }
            ],
            "rolls":1,
            "entries":[
                {
                    "type":"tag",
                    "name":"hats:hat_on_head",
                    "expand":true
                }
            ]
        }
    ]
}